gst_e_invoicing-0.9.0.dist-info/licenses/LICENSE
gst_irn/__init__.py
gst_irn/codes.py
gst_irn/converters.py
gst_irn/crypto.py
gst_irn/generators.py
gst_irn/qr.py
gst_irn/session.py
gst_e_invoicing-0.9.0.dist-info/METADATA
gst_e_invoicing-0.9.0.dist-info/WHEEL
gst_e_invoicing-0.9.0.dist-info/top_level.txt
gst_e_invoicing-0.9.0.dist-info/RECORD
