Metadata-Version: 2.4
Name: gst-e-invoicing
Version: 0.9.0
Summary: Python library for generating e-invoices using GST's E-invoicing portal.
Author-email: Mittal Analytics Pvt Ltd <pratyush@hey.com>
Project-URL: Homepage, https://github.com/Mittal-Analytics/gst-e-invoicing
Requires-Python: >=3.7
License-File: LICENSE
Requires-Dist: requests
Requires-Dist: cryptography
Requires-Dist: PyJWT
Requires-Dist: segno
Provides-Extra: dev
Requires-Dist: python-dotenv; extra == "dev"
Requires-Dist: flake8; extra == "dev"
Requires-Dist: black; extra == "dev"
Requires-Dist: ipdb; extra == "dev"
Requires-Dist: bumpver; extra == "dev"
Requires-Dist: build; extra == "dev"
Requires-Dist: twine; extra == "dev"
Dynamic: license-file
